LICENSE
MANIFEST.in
README.rst
setup.py
brutal/__init__.py
brutal/run.py
brutal.egg-info/PKG-INFO
brutal.egg-info/SOURCES.txt
brutal.egg-info/dependency_links.txt
brutal.egg-info/requires.txt
brutal.egg-info/top_level.txt
brutal/bin/brutal-overlord.py
brutal/conf/__init__.py
brutal/conf/global_config.py
brutal/core/__init__.py
brutal/core/bot.py
brutal/core/connections.py
brutal/core/constants.py
brutal/core/management.py
brutal/core/models.py
brutal/core/plugin.py
brutal/core/utils.py
brutal/plugins/__init__.py
brutal/plugins/auth.py
brutal/plugins/basic.py
brutal/plugins/logging_old.py
brutal/plugins/prodalert.py
brutal/plugins/twitter.py
brutal/protocols/__init__.py
brutal/protocols/core.py
brutal/protocols/hipbot.py
brutal/protocols/hipchat_test.py
brutal/protocols/irc.py
brutal/protocols/testconsole.py
brutal/protocols/xmpp.py
brutal/spawn/spawn_template/hive.py
brutal/spawn/spawn_template/spawn_name/__init__.py
brutal/spawn/spawn_template/spawn_name/config.py
brutal/spawn/spawn_template/spawn_name/plugins/__init__.py
brutal/spawn/spawn_template/spawn_name/plugins/example.py