Metadata-Version: 1.1
Name: brutal
Version: 0.3.3
Summary: a multi-network asynchronous chat bot framework using twisted.
Home-page: https://github.com/Netflix/brutal
Author: Corey Bertram
Author-email: corey@qr7.com
License: Copyright 2013 Corey Bertram and contributors.
